eamonn/__init__.py
eamonn/__version__.py
eamonn/eamonn.py
eamonn/ezsql.py
eamonn/test.py
eamonn-0.2.23.dist-info/LICENSE
eamonn-0.2.23.dist-info/METADATA
eamonn-0.2.23.dist-info/WHEEL
eamonn-0.2.23.dist-info/top_level.txt
eamonn-0.2.23.dist-info/RECORD
