Metadata-Version: 2.1
Name: eamonn
Version: 0.2.23
Summary: This is a method library that I wrote for myself.
Home-page: https://github.com/ChinaEamonn/MyLibrary
Author: eamonn
Author-email: china.eamonn@gmail.com
License: MIT
Platform: UNKNOWN
Classifier: License :: OSI Approved :: MIT License
Classifier: Programming Language :: Python
Classifier: Programming Language :: Python :: 3
Classifier: Programming Language :: Python :: 3.6
Classifier: Programming Language :: Python :: Implementation :: CPython
Classifier: Programming Language :: Python :: Implementation :: PyPy
Requires-Python: >=3.5.0
Requires-Dist: requests
Requires-Dist: flask
Requires-Dist: twine
Requires-Dist: PyMySQL
Requires-Dist: pymongo
